MANIFEST.in
README.rst
setup.py
aliyunsdkcs/__init__.py
aliyunsdkcs/request/__init__.py
aliyunsdkcs/request/v20151215/AddAgilityClusterRequest.py
aliyunsdkcs/request/v20151215/AttachInstancesRequest.py
aliyunsdkcs/request/v20151215/CallBackAgilityClusterRequest.py
aliyunsdkcs/request/v20151215/CallbackClusterTokenRequest.py
aliyunsdkcs/request/v20151215/CheckAliyunCSServiceRoleRequest.py
aliyunsdkcs/request/v20151215/CreateClusterRequest.py
aliyunsdkcs/request/v20151215/CreateClusterTokenRequest.py
aliyunsdkcs/request/v20151215/CreateTemplateRequest.py
aliyunsdkcs/request/v20151215/DeleteClusterNodeRequest.py
aliyunsdkcs/request/v20151215/DeleteClusterRequest.py
aliyunsdkcs/request/v20151215/DescribeAgilityTunnelAgentInfoRequest.py
aliyunsdkcs/request/v20151215/DescribeAgilityTunnelCertsRequest.py
aliyunsdkcs/request/v20151215/DescribeApiVersionRequest.py
aliyunsdkcs/request/v20151215/DescribeClusterCertsRequest.py
aliyunsdkcs/request/v20151215/DescribeClusterDetailRequest.py
aliyunsdkcs/request/v20151215/DescribeClusterHostsRequest.py
aliyunsdkcs/request/v20151215/DescribeClusterLogsRequest.py
aliyunsdkcs/request/v20151215/DescribeClusterNodeInfoRequest.py
aliyunsdkcs/request/v20151215/DescribeClusterNodeInfoWithInstanceRequest.py
aliyunsdkcs/request/v20151215/DescribeClusterNodesRequest.py
aliyunsdkcs/request/v20151215/DescribeClusterScaledNodeRequest.py
aliyunsdkcs/request/v20151215/DescribeClusterServicesRequest.py
aliyunsdkcs/request/v20151215/DescribeClusterTokensRequest.py
aliyunsdkcs/request/v20151215/DescribeClustersRequest.py
aliyunsdkcs/request/v20151215/DescribeImagesRequest.py
aliyunsdkcs/request/v20151215/DescribeServiceContainersRequest.py
aliyunsdkcs/request/v20151215/DescribeTaskInfoRequest.py
aliyunsdkcs/request/v20151215/DescribeTemplateAttributeRequest.py
aliyunsdkcs/request/v20151215/DescribeTemplatesRequest.py
aliyunsdkcs/request/v20151215/DescribeUserContainersRequest.py
aliyunsdkcs/request/v20151215/DownloadClusterNodeCertsRequest.py
dd_aliyun_python_sdk_cs.egg-info/PKG-INFO
dd_aliyun_python_sdk_cs.egg-info/SOURCES.txt
dd_aliyun_python_sdk_cs.egg-info/dependency_links.txt
dd_aliyun_python_sdk_cs.egg-info/pbr.json
dd_aliyun_python_sdk_cs.egg-info/requires.txt
dd_aliyun_python_sdk_cs.egg-info/top_level.txt